payments_tr/__init__.py
payments_tr/apps.py
payments_tr/cli.py
payments_tr/config.py
payments_tr/decorators.py
payments_tr/health.py
payments_tr/logging_config.py
payments_tr/models.py
payments_tr/py.typed
payments_tr/retry.py
payments_tr/security.py
payments_tr/signals.py
payments_tr/contrib/__init__.py
payments_tr/contrib/serializers.py
payments_tr/eft/__init__.py
payments_tr/eft/admin.py
payments_tr/eft/models.py
payments_tr/eft/services.py
payments_tr/management/__init__.py
payments_tr/management/commands/__init__.py
payments_tr/management/commands/check_providers.py
payments_tr/management/commands/cleanup_webhooks.py
payments_tr/management/commands/replay_webhooks.py
payments_tr/providers/__init__.py
payments_tr/providers/async_base.py
payments_tr/providers/base.py
payments_tr/providers/registry.py
payments_tr/providers/stripe.py
payments_tr/providers/iyzico/__init__.py
payments_tr/providers/iyzico/admin.py
payments_tr/providers/iyzico/apps.py
payments_tr/providers/iyzico/celeryconfig.py
payments_tr/providers/iyzico/client.py
payments_tr/providers/iyzico/currency.py
payments_tr/providers/iyzico/exceptions.py
payments_tr/providers/iyzico/models.py
payments_tr/providers/iyzico/monitoring.py
payments_tr/providers/iyzico/provider.py
payments_tr/providers/iyzico/serializers.py
payments_tr/providers/iyzico/settings.py
payments_tr/providers/iyzico/signals.py
payments_tr/providers/iyzico/tasks.py
payments_tr/providers/iyzico/urls.py
payments_tr/providers/iyzico/utils.py
payments_tr/providers/iyzico/views.py
payments_tr/providers/iyzico/viewsets.py
payments_tr/providers/iyzico/installments/__init__.py
payments_tr/providers/iyzico/installments/client.py
payments_tr/providers/iyzico/installments/urls.py
payments_tr/providers/iyzico/installments/utils.py
payments_tr/providers/iyzico/installments/views.py
payments_tr/providers/iyzico/management/__init__.py
payments_tr/providers/iyzico/management/commands/__init__.py
django_payments_tr-0.3.0.dist-info/METADATA
django_payments_tr-0.3.0.dist-info/WHEEL
django_payments_tr-0.3.0.dist-info/licenses/LICENSE
django_payments_tr-0.3.0.dist-info/RECORD
