Metadata-Version: 2.4
Name: django-payments-tr
Version: 0.3.0
Summary: Payment processing for Django with Turkey-specific features (iyzico, Stripe, EFT, KDV)
Project-URL: Homepage, https://github.com/aladagemre/django-payments-tr
Project-URL: Documentation, https://github.com/aladagemre/django-payments-tr#readme
Project-URL: Repository, https://github.com/aladagemre/django-payments-tr
Project-URL: Issues, https://github.com/aladagemre/django-payments-tr/issues
Author-email: Emre Aladağ <emre@aladagemre.com>
License-Expression: MIT
License-File: LICENSE
Keywords: django,eft,iyzico,kdv,payments,stripe,turkey,vat
Classifier: Development Status :: 3 - Alpha
Classifier: Environment :: Web Environment
Classifier: Framework :: Django
Classifier: Framework :: Django :: 4.2
Classifier: Framework :: Django :: 5.0
Classifier: Framework :: Django :: 5.1
Classifier: Intended Audience :: Developers
Classifier: License :: OSI Approved :: MIT License
Classifier: Operating System :: OS Independent
Classifier: Programming Language :: Python :: 3
Classifier: Programming Language :: Python :: 3.12
Classifier: Programming Language :: Python :: 3.13
Classifier: Topic :: Office/Business :: Financial
Classifier: Topic :: Software Development :: Libraries :: Python Modules
Requires-Python: >=3.12
Requires-Dist: django>=4.2
Provides-Extra: all
Requires-Dist: iyzipay>=1.0; extra == 'all'
Requires-Dist: stripe>=5.0; extra == 'all'
Provides-Extra: dev
Requires-Dist: black>=24.0; extra == 'dev'
Requires-Dist: celery>=5.6.0; extra == 'dev'
Requires-Dist: django-stubs>=4.2; extra == 'dev'
Requires-Dist: djangorestframework>=3.14; extra == 'dev'
Requires-Dist: isort>=5.0; extra == 'dev'
Requires-Dist: iyzipay>=1.0; extra == 'dev'
Requires-Dist: mypy>=1.8; extra == 'dev'
Requires-Dist: pytest-asyncio>=0.23.0; extra == 'dev'
Requires-Dist: pytest-cov>=4.0; extra == 'dev'
Requires-Dist: pytest-django>=4.5; extra == 'dev'
Requires-Dist: pytest>=8.0; extra == 'dev'
Requires-Dist: ruff>=0.1.0; extra == 'dev'
Requires-Dist: stripe>=5.0; extra == 'dev'
Provides-Extra: iyzico
Requires-Dist: iyzipay>=1.0; extra == 'iyzico'
Provides-Extra: stripe
Requires-Dist: stripe>=5.0; extra == 'stripe'
